tsimporter-0.1.3.dist-info/METADATA
tsimporter-0.1.3.dist-info/WHEEL
tsimporter-0.1.3.dist-info/entry_points.txt
tsimporter/__init__.py
tsimporter/importer.py
tsimporter/logging_config.py
tsimporter-0.1.3.dist-info/RECORD
