Metadata-Version: 2.1
Name: tsimporter
Version: 0.1.3
Summary: Local files to database.
Author-Email: Taeyong Jeon <taeyongjeon24@gmail.com>
License: MIT
Project-URL: Repository, https://github.com/tyjeon24/tsimporter
Requires-Python: >=3.10
Requires-Dist: pandas>=2.2.3
Requires-Dist: psycopg2-binary>=2.9.10
Requires-Dist: pyarrow>=18.0.0
Requires-Dist: fastparquet>=2024.5.0
